[
  {
    "image": "../../kahvalti.JPG",
    "title": "Kahvaltılar",
    "category": "Yemekler",
    "products": [
      {
        "headingText": "Sade Kahvaltı",
        "descriptionText": "Beyaz Peynir, Kaşar Peyniri, Domates, Salatalık, Siyah-Yeşil Zeytin, Tereyaği, Bal, Reçel, Çikolata, Haşlanmış Yumurta, Kruvasan, Fincan Çay",
        "price": "200"
      },
      {
        "headingText": "Pancake Kahvaltı",
        "descriptionText": "4 adet Pancake, Beyaz Peynir, Kaşar Peyniri, Çeçil Peynir, Domates, Salatalık, Siyah-Yeşil Zeytin, Tereyaği, Bal, Reçel, Çikolata, Muz, Çilek, Fincan Çay",
        "price": "225"
      },
      {
        "headingText": "Serpme Kahvaltı",
        "descriptionText": "(EN AZ 2 KİŞİLİK) Beyaz Peynir, Ezine Peyniri, Kaşar Peyniri, Çeçil Peynir, Top Peynir, Çubuk Peynir, Domates, Salatalık, Yeşil-Siyah Zeytin, Terayaği, Kaymak, Bal, İki Çesit Reçel, Çikolata, Kızarmış Patates, Sigara Böreği, Sosis, Menemen, Omlet, Gözleme, Termos Çay",
        "price": "450"
      },
      {
        "headingText": "Günbatımı Special",
        "descriptionText": "(4 KİŞİLİK) Beyaz Penir, Ezine Peyniri, Kaşar Peyniri, Çeçil Peynir, Top Peynir, Çubuk Peynir, Domates, Salatalık, Yeşil-Siyah Zeytin, Terayaği, Kaymak, Bal, Iki Çesit Reçel, Çikolata, Kızarmış Patates, Sigara Böreği, Sosis, Menemen, Omlet, Gözleme, Termos Çay",
        "price": "1,450"
      },
      {
        "image": "../../omlet.JPG",
        "headingText": "Omlet",
        "price": "85"
      },
      {
        "image": "../../sebzeli-omlet.JPG",
        "headingText": "Karısık Sebzeli Omlet",
        "price": "95"
      },
      {
        "image": "../../beyaz-omlet.JPG",
        "headingText": "Beyaz Fit Omlet",
        "price": "110"
      },
      {
        "image": "../../gozleme-tabak.JPG",
        "headingText": "Patates Kaşarli Gözleme",
        "price": "95"
      },
      {
        "image": "../../sigara-boregi.JPG",
        "headingText": "Sigara Böreği",
        "price": "95"
      },
      {
        "image": "../../sosis-tabak.JPG",
        "headingText": "Kızarmış Sosis Tabağı",
        "price": "125"
      },
      {
        "image": "../../su-boregi.JPG",
        "headingText": "Su Böreği(Tepsi)",
        "price": "600"
      },
      {
        "headingText": "Bal Kaymak Tabağı",
        "price": "85"
      },
      {
        "headingText": "Peynir Tabağı",
        "price": "95"
      },
      {
        "headingText": "Meyve Tabağı",
        "price": "95"
      },
      {
        "headingText": "Menemen",
        "price": "95"
      },
      {
        "headingText": "Sucuklu Yumurta",
        "price": "125"
      },
      {
        "headingText": "Sucuk Tava",
        "price": "145"
      },
      {
        "headingText": "Kuymak",
        "price": "175"
      },
      {
        "headingText": "Pankek",
        "price": "125"
      },
      {
        "headingText": "Kaşarlı Gözleme",
        "price": "85"
      },
      {
        "headingText": "Patatesli Gözleme",
        "price": "95"
      },
      {
        "headingText": "Parmak Patates",
        "price": "85"
      },
      {
        "headingText": "Elma Dilim Patates",
        "price": "85"
      },
      {
        "headingText": "Soğan Halkası(İthal)",
        "price": "105"
      }
    ]
  },
  {
    "image": "../../tostlar.JPG",
    "title": "Tostlar ve Sandwichler",
    "category": "Yemekler",
    "products": [
      {
        "image": "../../tost.JPG",
        "headingText": "Günbatımı Special Tost",
        "descriptionText": "Karısık Tost, Patetes Kızartması, İthal Soğan Halkası, Yeşillik, Çay veya Ayran",
        "price": "145"
      },
      {
        "image": "../../tost-ayvalik.JPG",
        "headingText": "Ayvalık Tostu",
        "descriptionText": "Patates Kızartması, Yeşillik",
        "price": "145"
      },
      {
        "image": "../../tost-light.JPG",
        "headingText": "Light Tost",
        "descriptionText": "Kaşar Peynirli Tost, Yeşillik",
        "price": "110"
      },
      {
        "headingText": "Sucuklu Tost",
        "descriptionText": "Patates Kızartması, Yeşillik",
        "price": "95"
      },
      {
        "headingText": "Kaşarlı Tost",
        "descriptionText": "Patates Kızartması, Yeşillik",
        "price": "95"
      },
      {
        "headingText": "Karışık Tost",
        "descriptionText": "Patates Kızartması, Yeşillik",
        "price": "110"
      },
      {
        "headingText": "Duble Tost",
        "descriptionText": "Patates Kızartması, Yeşillik",
        "price": "125"
      },
      {
        "headingText": "Patatesli Sandwich",
        "descriptionText": "Patates, Turşu, Ketçap, Mayonez",
        "price": "95"
      },
      {
        "headingText": "Salam-Kaşarlı Sandwich",
        "descriptionText": "Salam, Kaşar Peyniri, Domates, Yeşillik",
        "price": "110"
      },
      {
        "headingText": "Beyaz Peynirli Sandwich",
        "descriptionText": "Beyaz Peynir, Domates, Salatalık, Yeşillik",
        "price": "95"
      },
      {
        "headingText": "Kumru",
        "descriptionText": "Salam, Sucuk, Sosis, Karnison Turşu, Eritilmiş Kaşar",
        "price": "145"
      }
    ]
  },
  {
    "image": "../../burger.JPG",
    "title": "Burgerler",
    "category": "Yemekler",
    "products": [
      {
        "image": "../../burger.JPG",
        "headingText": "Günbatımı Special Burger",
        "descriptionText": "Duble Burger, Cheddar Peyniri, Marul, Domates, Soğan, Kızarmış Patates, Soğan Halkası, Yeşillik",
        "price": "175"
      },
      {
        "image": "../../burger-cheese.JPG",
        "headingText": "Cheese Burger",
        "descriptionText": "Marul, Domates, Turşu, Ketçap, Mayonez, Cheddar Peyniri, Kızarmış Patates, Soğan Halkası, Yeşillik",
        "price": "155"
      },
      {
        "headingText": "Hamburger",
        "descriptionText": "Marul, Domates, Turşu, Ketçap, Mayonez, Kızarmış Patates, Soğan Halkası, Yeşillik",
        "price": "135"
      },
      {
        "headingText": "Piliç Burger",
        "descriptionText": "Izgara Piliç, Cheddar Peyniri, Domates, Marul, Turşu, Ketçap, Mayonez, Kızarmış Patates, Soğan Halkası, Yeşillik",
        "price": "175"
      }
    ]
  },
  {
    "image": "../../pizza.JPG",
    "title": "Pizzalar",
    "category": "Yemekler",
    "products": [
      {
        "headingText": "Margherita Pizza",
        "descriptionText": "Domates Sos, Fesleğen, Mozarella Peyniri",
        "price": "175"
      },
      {
        "headingText": "Pizza de Luxe",
        "descriptionText": "Domates Sos, Sucuk, Salam, Yeşil Biber, Siyah Zeytin",
        "price": "200"
      },
      {
        "headingText": "Pizza Jamaican",
        "descriptionText": "Domates Sos, Sosis, Mozarella Peyniri",
        "price": "175"
      },
      {
        "headingText": "Pizza Queen",
        "descriptionText": "Domates Sos, Sucuk, Mantar, Mozarella Peyniri, Kekik",
        "price": "175"
      },
      {
        "headingText": "Ton Balıklı Pizza",
        "descriptionText": "Domates Sos, Ton Balığı, Mısır, Siyah Zeytin",
        "price": "245"
      },
      {
        "headingText": "Vejeteryan Pizza",
        "descriptionText": "Domates Sos, Mevsim Sebzeleri, Mozarella Peyniri",
        "price": "175"
      },
      {
        "headingText": "Günbatimi Pizza",
        "descriptionText": "Domates Sos, Dana Jambon, Sucuk, Yeşil Biber, Mantar, Siyah Zeytin, Kekik, Mozarella Peyniri",
        "price": "225"
      }
    ]
  },
  {
    "image": "../../durum.JPG",
    "title": "Dürümler",
    "category": "Yemekler",
    "products": [
      {
        "image": "../../durum.JPG",
        "headingText": "Etli Beyti Dürüm",
        "descriptionText": "Dana Eti, Biber, Mantar, Domates, Yoğurt, Izgara Domates ve Biber",
        "price": "275"
      },
      {
        "image": "../../durum-tavuk.JPG",
        "headingText": "Special Tavuk Dürüm",
        "descriptionText": "Tavuk Eti, Biber, Mantar, Domates, Patates Kızartması, Soğan Halkası",
        "price": "225"
      },
      {
        "headingText": "Special Etli Dürüm",
        "descriptionText": "Dana Eti, Biber, Mantar, Domates, Patates Kızartması, Soğan Halkası",
        "price": "250"
      },
      {
        "headingText": "Tavuk Etli Beyti Dürüm",
        "descriptionText": "Tavuk Eti, Biber, Mantar, Domates, Yoğurt, Izgara Domates ve Biber",
        "price": "225"
      }
    ]
  },
  {
    "image": "../../alacarte.JPG",
    "title": "À la Carte",
    "category": "Yemekler",
    "products": [
      {
        "image": "../../tavuk-kori.JPG",
        "headingText": "Köri Soslu Tavuk",
        "descriptionText": "Tavuk, Biber, Mantar, Makarna, Yeşillik",
        "price": "225"
      },
      {
        "image": "../../tavuk-mushroom.JPG",
        "headingText": "Chicken Mushroom",
        "descriptionText": "Izgara Tavuk, Eritilmiş Kaşar Peyniri, Soya soslu Kremalı Mantar, Makarna, Yeşillik",
        "price": "225"
      },
      {
        "image": "../../tavuk-pesto.JPG",
        "headingText": "Pesto Soslu Tavuk",
        "descriptionText": "Tavuk, Biber, Mantar, Pesto Sos, Makarna, Yeşillik",
        "price": "225"
      },
      {
        "image": "../../tavuk-soya.JPG",
        "headingText": "Soya Soslu Tavuk",
        "descriptionText": "Tavuk, Biber, Soya Soslu Makarna, Yeşillik",
        "price": "225"
      },
      {
        "image": "../../et-sinitzel.JPG",
        "headingText": "Et Şinitzel",
        "descriptionText": "Fileto Et, Baby Patates, Yeşillik",
        "price": "250"
      },
      {
        "image": "../../tavuk-sinitzel.JPG",
        "headingText": "Tavuk Şinitzel",
        "descriptionText": "Fileto Tavuk, Baby Patates, Yeşillik",
        "price": "225"
      },
      {
        "image": "../../fajita-combo.JPG",
        "headingText": "Combo Fajita",
        "descriptionText": "Jülyen Et, Tavuk, Biber, Patlıcan, Kabak, Soğan, Soya Sos",
        "price": "275"
      },
      {
        "headingText": "Etli Fajita",
        "descriptionText": "Jülyen Et, Biber, Patlıcan, Kabak, Soğan, Soya Sos",
        "price": "250"
      },
      {
        "headingText": "Tavuklu Fajita",
        "descriptionText": "Tavuk, Biber, Patlıcan, Kabak, Soğan, Soya Sos",
        "price": "250'"
      }
    ]
  },
  {
    "image": "../../izgaralar.JPG",
    "title": "Izgaralar",
    "category": "Yemekler",
    "products": [
      {
        "image": "../../kofte-izgara.JPG",
        "headingText": "Izgara Köfte",
        "descriptionText": "5 Adet Kasap Köfte, Baby, Patates, Bulgur Pilavı, Izgara Biber ve Domates, Yeşillik",
        "price": "225"
      },
      {
        "image": "../../izgara.JPG",
        "headingText": "Karısık Izgara Tabağı",
        "descriptionText": "Kasap Köfte, Çöp Şiş, Tavuk Şiş, Sucuk, Baby Patates, Bulgur Pilavı, Izgara Biber ve Domates, Yeşillik",
        "price": "280"
      },
      {
        "image": "../../tavuk-izgara-kulbasti.JPG",
        "headingText": "Izgara Tavuk Külbastı",
        "descriptionText": "Tavuk Külbastı, Bulgur Pilavı, Baby Patates, Izgara Biber ve Domates, Yeşillik",
        "price": "225"
      },
      {
        "image": "../../tavuk-izgara-pesto.JPG",
        "headingText": "Izgara Pesto Soslu Piliç",
        "descriptionText": "Izgara Piliç, Pesto Sos, Cheddar Peyniri, Bulgur Pilavı, Baby Patates, Izgara Biber ve Domates, Yeşillik",
        "price": "225"
      },
      {
        "image": "../../tavuk-sis.JPG",
        "headingText": "Izgara Tavuk Şiş",
        "descriptionText": "2 Adet Tavuk Şiş, Baby Patates, Bulgur Pilavı, Izgara Biber ve Domates, Yeşillik",
        "price": "175"
      },
      {
        "image": "../../izgara-pastirma.JPG",
        "headingText": "Pastırmalı Kaşarlı Köfte",
        "descriptionText": "2 Adet Kaşarlı Köfte, Pastırma, Tırnak Pide, Soğan, Domates Sos, Yoğurt, Izgara Biber ve Domates",
        "price": "250"
      }
    ]
  },
  {
    "image": "../../makarnalar.JPG",
    "title": "Makarnalar",
    "category": "Yemekler",
    "products": [
      {
        "image": "../../makarna.JPG",
        "headingText": "Penne Pesto Porcini",
        "descriptionText": "Penne Makarna, Tavuk, Mantar, Krema, Pesto Sos",
        "price": "175"
      },
      {
        "image": "../../makarna-fettucine.JPG",
        "headingText": "Fettucine",
        "descriptionText": "Fettucine Makarna, Tavuk, Mantar, Fesleğen, Parmesan Peyniri",
        "price": "175"
      },
      {
        "image": "../../makarna-kori-penne.JPG",
        "headingText": "Kori Soslu Penne Makarna",
        "descriptionText": "Penne Makarna, Krema, Kori Sos, Parmesan Peyniri",
        "price": "150"
      },
      {
        "image": "../../makarna-bolonez.JPG",
        "headingText": "Spagetti Bolonez",
        "descriptionText": "Spagetti Makarna, Domates Soslu Dana Kıyma, Parmesan Peyniri",
        "price": "225"
      },
      {
        "image": "../../manti.JPG",
        "headingText": "Mantı",
        "price": "175"
      },
      {
        "image": "../../manti-citir.JPG",
        "headingText": "Çıtır Mantı",
        "price": "250"
      },
      {
        "headingText": "Penne Arabiata",
        "descriptionText": "Penne Makarna, Acı Sos, Parmesan, Fesleğen",
        "price": "150"
      },
      {
        "headingText": "Chicken Alfredo Tagliatelle",
        "descriptionText": "Taglietelle Makarna, Izgara Tavuk, Alfredo Sos, Parmesan Peyniri",
        "price": "225"
      }
    ]
  },
  {
    "image": "../../salata.JPG",
    "title": "Salatalar",
    "category": "Yemekler",
    "products": [
      {
        "image": "../../salata-beyaz-peynir.JPG",
        "headingText": "Beyaz Peynirli Salata",
        "descriptionText": "Yeşillik, Salatalık, Domates, Siyah Zeytin, Beyaz Peynir",
        "price": "175"
      },
      {
        "image": "../../salata-ton.JPG",
        "headingText": "Ton Balıklı Salata",
        "descriptionText": "Yeşillik, Salatalık, Domates, Mısır, Siyah Zeytin, Ton Balığı",
        "price": "225"
      },
      {
        "image": "../../salata-bugday.JPG",
        "headingText": "Buğday Salata",
        "descriptionText": "Yeşillik, Salatalık, Domates, Fındık Turp, Siyah Zeytin, Buğday",
        "price": "225"
      },
      {
        "image": "../../salata-kinoa.JPG",
        "headingText": "Kinoa Salata",
        "descriptionText": "Yeşillik, Domates, Ceviz, Badem, Avokado, Kinoa",
        "price": "225"
      },
      {
        "image": "../../salata-sezar.JPG",
        "headingText": "Tavuklu Sezar Salata",
        "descriptionText": "Yeşillik, Salatalık, Kruton Sezar Sos, Izgara Tavuk",
        "price": "225"
      },
      {
        "image": "../../salata-izgara.JPG",
        "headingText": "Izgara Hellim Salata",
        "descriptionText": "Yeşillik, Salatalık, Domates, Mısır, Hellim Peyniri",
        "price": "225"
      }
    ]
  },
  {
    "image": "../../tatli.PNG",
    "title": "Tatlılar",
    "category": "Tatlılar",
    "products": [
      {
        "headingText": "Magnolia",
        "price": "75"
      },
      {
        "headingText": "Supangle",
        "price": "75"
      },
      {
        "headingText": "Profiterol",
        "price": "75"
      },
      {
        "headingText": "Tiramisu",
        "price": "75"
      },
      {
        "headingText": "Truf Çikolatalı Pasta",
        "price": "95"
      },
      {
        "headingText": "Mozaik Pasta",
        "price": "95"
      },
      {
        "headingText": "Cheesecake",
        "price": "95"
      },
      {
        "headingText": "Mois Pasta",
        "price": "125"
      },
      {
        "headingText": "Ibiza",
        "price": "125"
      },
      {
        "headingText": "Fıstık Rüyası",
        "price": "95"
      },
      {
        "headingText": "Malaga",
        "price": "125"
      },
      {
        "headingText": "Bella Vista",
        "price": "75"
      },
      {
        "headingText": "Trileçe",
        "price": "75"
      },
      {
        "headingText": "Sufle",
        "price": "95"
      },
      {
        "headingText": "Budapeşte",
        "price": "125"
      },
      {
        "headingText": "Noel Sarma",
        "price": "125"
      }
    ]
  },
  {
    "image": "../../kokteyl.PNG",
    "title": "Kokteyller",
    "category": "İçecekler",
    "products": [
      {
        "headingText": "Mojito",
        "price": "125"
      },
      {
        "headingText": "Çilekli Mojito",
        "price": "125"
      },
      {
        "headingText": "Mysterious Passion",
        "price": "125"
      },
      {
        "headingText": "Globetrotter",
        "price": "125"
      },
      {
        "headingText": "East Garden",
        "price": "125"
      },
      {
        "headingText": "The Red Bush",
        "price": "125"
      }
    ]
  },
  {
    "image": "../../sicak-icecek.PNG",
    "title": "Sıcak İçecekler",
    "category": "İçecekler",
    "products": [
      {
        "headingText": "Çay",
        "price": "19"
      },
      {
        "headingText": "Meyve Çaylari",
        "price": "35"
      },
      {
        "headingText": "Double Çay",
        "price": "35"
      },
      {
        "headingText": "Bitki Çayları",
        "price": "55"
      },
      {
        "headingText": "Türk Kahvesi",
        "price": "55"
      },
      {
        "headingText": "Espresso",
        "price": "45"
      },
      {
        "headingText": "Espresso Americano",
        "price": "75"
      },
      {
        "headingText": "Nescafe",
        "price": "65"
      },
      {
        "headingText": "Filtre Kahve",
        "price": "75"
      },
      {
        "headingText": "Sütlü Filtre Kahve",
        "price": "75"
      },
      {
        "headingText": "Caffé Latte",
        "price": "90"
      },
      {
        "headingText": "Cappucino",
        "price": "90"
      },
      {
        "headingText": "Caffé Macchiato",
        "price": "90"
      },
      {
        "headingText": "Caffé Mocha",
        "price": "90"
      },
      {
        "headingText": "Salep",
        "price": "90"
      },
      {
        "headingText": "Hot Chocolate",
        "price": "90"
      },
      {
        "headingText": "White Chocolate",
        "price": "90"
      },
      {
        "headingText": "Süt",
        "price": "60"
      }
    ]
  },
  {
    "image": "../../soguk-icecek.PNG",
    "title": "Soğuk İçecekler",
    "category": "İçecekler",
    "products": [
      {
        "headingText": "Kola, Fanta, Gazoz",
        "price": "65"
      },
      {
        "headingText": "Ice Tea",
        "price": "65"
      },
      {
        "headingText": "Meyve Suyu",
        "price": "65"
      },
      {
        "headingText": "Portakal Suyu",
        "price": "90"
      },
      {
        "headingText": "Limonata",
        "price": "90"
      },
      {
        "headingText": "Çilekli Limonata",
        "price": "90"
      },
      {
        "headingText": "Kivili Limonata",
        "price": "90"
      },
      {
        "headingText": "Yeşil Elmalı Limonata",
        "price": "90"
      },
      {
        "headingText": "Red Bull",
        "price": "90"
      },
      {
        "headingText": "Meyveli Soda",
        "price": "45"
      },
      {
        "headingText": "Sade Soda",
        "price": "45"
      },
      {
        "headingText": "Ayran",
        "price": "40"
      },
      {
        "headingText": "Su",
        "price": "15"
      }
    ]
  },
  {
    "image": "../../milkshake.PNG",
    "title": "Milkshake",
    "category": "İçecekler",
    "products": [
      {
        "headingText": "Çilekli Milkshake",
        "price": "90"
      },
      {
        "headingText": "Oreolu Milkshake",
        "price": "90"
      },
      {
        "headingText": "Çikolatalı Milkshake",
        "price": "90"
      },
      {
        "headingText": "Bal Bademli Milkshake",
        "price": "90"
      },
      {
        "headingText": "Muzlu Milkshake",
        "price": "90"
      }
    ]
  },
  {
    "image": "../../frozen.PNG",
    "title": "Frozen",
    "category": "İçecekler",
    "products": [
      {
        "headingText": "Çilekli Frozen",
        "price": "90"
      },
      {
        "headingText": "Yeşil Elmalı Frozen",
        "price": "90"
      },
      {
        "headingText": "Limonlu Frozen",
        "price": "90"
      },
      {
        "headingText": "Kivili Frozen",
        "price": "90"
      },
      {
        "headingText": "Karpuzlu Frozen",
        "price": "90"
      },
      {
        "headingText": "Orman Meyveli Frozen",
        "price": "90"
      },
      {
        "headingText": "Ananaslı Frozen",
        "price": "90"
      },
      {
        "headingText": "Çarkıfelek Frozen",
        "price": "90"
      }
    ]
  },
  {
    "image": "../../smoothie.PNG",
    "title": "Smoothie",
    "category": "İçecekler",
    "products": [
      {
        "headingText": "Çilekli Smoothie",
        "price": "125"
      },
      {
        "headingText": "Çikolatalı Smoothie",
        "price": "125"
      },
      {
        "headingText": "Muzlu Smoothie",
        "price": "125"
      }
    ]
  },
  {
    "image": "../../soguk-kahve.png",
    "title": "Soğuk Kahveler",
    "category": "İçecekler",
    "products": [
      {
        "headingText": "Ice Latte",
        "price": "90"
      },
      {
        "headingText": "Ice Mocha",
        "price": "90"
      },
      {
        "headingText": "Ice Americano",
        "price": "90"
      }
    ]
  },
  {
    "image": "../../dondurma.png",
    "title": "Dondurmalar",
    "category": "Yiyecek",
    "products": [
      {
        "headingText": "Vanilya - 1 top",
        "price": "25"
      },
      {
        "headingText": "Çilek - 1 top",
        "price": "25"
      },
      {
        "headingText": "Antep fıstıklı - 1 top",
        "price": "25"
       }
    ]
  }
]
